qlligraphy/__init__.py
qlligraphy/core/__init__.py
qlligraphy/core/ast_node_context.py
qlligraphy/core/base/__init__.py
qlligraphy/core/base/visitor.py
qlligraphy/core/constants.py
qlligraphy/core/graphql_schema_visitor.py
qlligraphy/core/py_ast_builders.py
qlligraphy/core/visit_functions.py
qlligraphy/main.py
qlligraphy-0.1.3.dist-info/entry_points.txt
qlligraphy-0.1.3.dist-info/LICENSE
qlligraphy-0.1.3.dist-info/WHEEL
qlligraphy-0.1.3.dist-info/METADATA
qlligraphy-0.1.3.dist-info/RECORD
